jax_dataloader/__init__.py
jax_dataloader/_modidx.py
jax_dataloader/core.py
jax_dataloader/datasets.py
jax_dataloader/imports.py
jax_dataloader/tests.py
jax_dataloader/types.py
jax_dataloader/utils.py
jax_dataloader/experimental/__init__.py
jax_dataloader/experimental/multi_processing.py
jax_dataloader/loaders/__init__.py
jax_dataloader/loaders/base.py
jax_dataloader/loaders/jax.py
jax_dataloader/loaders/tensorflow.py
jax_dataloader/loaders/torch.py
jax_dataloader-0.1.4.dist-info/LICENSE
jax_dataloader-0.1.4.dist-info/METADATA
jax_dataloader-0.1.4.dist-info/WHEEL
jax_dataloader-0.1.4.dist-info/entry_points.txt
jax_dataloader-0.1.4.dist-info/top_level.txt
jax_dataloader-0.1.4.dist-info/RECORD
