Metadata-Version: 2.2
Name: jax-dataloader
Version: 0.1.4
Summary: Dataloader for jax
Home-page: https://github.com/birkhoffg/jax-dataloader
Author: BirkhoffG
Author-email: 26811230+BirkhoffG@users.noreply.github.com
License: Apache Software License 2.0
Keywords: python jax dataloader pytorch tensorflow datasets huggingface
Classifier: Development Status :: 4 - Beta
Classifier: Intended Audience :: Developers
Classifier: Natural Language :: English
Classifier: Programming Language :: Python :: 3.8
Classifier: Programming Language :: Python :: 3.9
Classifier: Programming Language :: Python :: 3.10
Classifier: Programming Language :: Python :: 3.11
Classifier: Programming Language :: Python :: 3.12
Classifier: License :: OSI Approved :: Apache Software License
Requires-Python: >=3.8
License-File: LICENSE
Requires-Dist: jax
Requires-Dist: plum-dispatch
Provides-Extra: all
Requires-Dist: jax; extra == "all"
Requires-Dist: plum-dispatch; extra == "all"
Requires-Dist: tensorflow; extra == "all"
Requires-Dist: tensorflow-datasets; extra == "all"
Requires-Dist: datasets; extra == "all"
Requires-Dist: numpy<2.0.0; extra == "all"
Requires-Dist: torch; extra == "all"
Requires-Dist: torchvision; extra == "all"
Requires-Dist: scikit-learn; extra == "all"
Requires-Dist: pandas; extra == "all"
Requires-Dist: nbdev; extra == "all"
Requires-Dist: jupyter; extra == "all"
Requires-Dist: dm-haiku; extra == "all"
Requires-Dist: optax; extra == "all"
Requires-Dist: flax; extra == "all"
Provides-Extra: dev
Requires-Dist: jax; extra == "dev"
Requires-Dist: plum-dispatch; extra == "dev"
Requires-Dist: tensorflow; extra == "dev"
Requires-Dist: tensorflow-datasets; extra == "dev"
Requires-Dist: datasets; extra == "dev"
Requires-Dist: numpy<2.0.0; extra == "dev"
Requires-Dist: torch; extra == "dev"
Requires-Dist: torchvision; extra == "dev"
Requires-Dist: scikit-learn; extra == "dev"
Requires-Dist: pandas; extra == "dev"
Requires-Dist: nbdev; extra == "dev"
Requires-Dist: jupyter; extra == "dev"
Requires-Dist: dm-haiku; extra == "dev"
Requires-Dist: optax; extra == "dev"
Requires-Dist: flax; extra == "dev"
Provides-Extra: tensorflow
Requires-Dist: tensorflow; extra == "tensorflow"
Requires-Dist: tensorflow-datasets; extra == "tensorflow"
Provides-Extra: huggingface
Requires-Dist: datasets; extra == "huggingface"
Requires-Dist: numpy<2.0.0; extra == "huggingface"
Provides-Extra: torch
Requires-Dist: torch; extra == "torch"
Requires-Dist: torchvision; extra == "torch"
Dynamic: author
Dynamic: author-email
Dynamic: classifier
Dynamic: description
Dynamic: description-content-type
Dynamic: home-page
Dynamic: keywords
Dynamic: license
Dynamic: provides-extra
Dynamic: requires-dist
Dynamic: requires-python
Dynamic: summary
